tiktok_captcha_solver_fork/__init__.py
tiktok_captcha_solver_fork/api.py
tiktok_captcha_solver_fork/asyncplaywrightsolver.py
tiktok_captcha_solver_fork/asyncsolver.py
tiktok_captcha_solver_fork/captchatype.py
tiktok_captcha_solver_fork/download_crx.py
tiktok_captcha_solver_fork/downloader.py
tiktok_captcha_solver_fork/geometry.py
tiktok_captcha_solver_fork/launcher.py
tiktok_captcha_solver_fork/models.py
tiktok_captcha_solver_fork/nodriversolver.py
tiktok_captcha_solver_fork/playwrightsolver.py
tiktok_captcha_solver_fork/selectors.py
tiktok_captcha_solver_fork/seleniumsolver.py
tiktok_captcha_solver_fork/solver.py
tiktok_captcha_solver_fork/tests/__init__.py
tiktok_captcha_solver_fork/tests/test_api.py
tiktok_captcha_solver_fork/tests/test_asyncplaywrightsolver.py
tiktok_captcha_solver_fork/tests/test_download_crx.py
tiktok_captcha_solver_fork/tests/test_downloader.py
tiktok_captcha_solver_fork/tests/test_launcher.py
tiktok_captcha_solver_fork/tests/test_playwrightsolver.py
tiktok_captcha_solver_fork/tests/test_seleniumsolver.py
tiktok_captcha_solver_fork-0.8.7.dist-info/METADATA
tiktok_captcha_solver_fork-0.8.7.dist-info/WHEEL
tiktok_captcha_solver_fork-0.8.7.dist-info/top_level.txt
tiktok_captcha_solver_fork-0.8.7.dist-info/RECORD
