Metadata-Version: 2.4
Name: tiktok-captcha-solver-fork
Version: 0.8.7
Summary: This package integrates with Selenium or Playwright to solve any TikTok captcha in one line of code.
Author-email: Toughdata LLC <greg@toughdata.net>
License-Expression: MIT
Project-URL: Homepage, https://www.sadcaptcha.com
Project-URL: Source, https://github.com/outlandishdigital/tiktok-captcha-solver
Project-URL: Bug Reports, https://github.com/outlandishdigital/tiktok-captcha-solver/issues
Keywords: tiktok,captcha,solver,selenium,rotate,puzzle,3d
Classifier: Development Status :: 4 - Beta
Classifier: Intended Audience :: Developers
Classifier: Topic :: Software Development :: Build Tools
Classifier: Programming Language :: Python :: 3
Classifier: Programming Language :: Python :: 3.10
Classifier: Programming Language :: Python :: 3.11
Classifier: Programming Language :: Python :: 3.12
Classifier: Programming Language :: Python :: 3 :: Only
Requires-Python: >=3.10
Requires-Dist: selenium
Requires-Dist: webdriver-manager
Requires-Dist: pydantic
Requires-Dist: requests
Requires-Dist: pytest
Requires-Dist: pytest-asyncio
Requires-Dist: playwright
Requires-Dist: playwright-stealth
Requires-Dist: undetected_chromedriver
Requires-Dist: setuptools
Requires-Dist: nodriver
Requires-Dist: zendriver
